bakhtawar/__init__.py
bakhtawar/app.py
bakhtawar-0.0.1.dist-info/METADATA
bakhtawar-0.0.1.dist-info/WHEEL
bakhtawar-0.0.1.dist-info/licenses/LICENSE
bakhtawar-0.0.1.dist-info/RECORD
