Metadata-Version: 2.1
Name: bakhtawar
Version: 0.0.1
Summary: This is where magic happens
Author-email: Bakhtawar <dhaansugroup007@gmail.com>
License-File: LICENSE
Classifier: License :: OSI Approved :: MIT License
Classifier: Operating System :: OS Independent
Classifier: Programming Language :: Python :: 3
Requires-Python: >=3.7
